customized_table/__init__.py
customized_table/customized_table.py
customized_table/docs.py
customized_table-0.1.17.dist-info/LICENSE
customized_table-0.1.17.dist-info/METADATA
customized_table-0.1.17.dist-info/WHEEL
customized_table-0.1.17.dist-info/top_level.txt
customized_table-0.1.17.dist-info/RECORD
