Metadata-Version: 2.1
Name: customized-table
Version: 0.1.17
Summary: Creates flexible tables in Jupyter Notebooks with lots of formatting options
Home-page: https://github.com/jhagelback/customized_table
Author: Johan Hagelbäck
Author-email: johan.hagelback@gmail.com
License: MIT
License-File: LICENSE
Requires-Dist: termcolor
Requires-Dist: help-generator
